hough3d/__init__.py
hough3d/basic_hough.py
hough3d/line_segment_hough.py
hough3d/spatial.py
hough3d/utils.py
hough3d-1.0.0.dist-info/METADATA
hough3d-1.0.0.dist-info/WHEEL
hough3d-1.0.0.dist-info/top_level.txt
hough3d-1.0.0.dist-info/RECORD
