Metadata-Version: 2.1
Name: hough3d
Version: 1.0.0
Summary: Library for detecting lines in a 3D point cloud via Hough transform.
Home-page: https://github.com/jfeatherstone/hough3d
Author: Jack Featherstone
Author-email: jack.featherstone@oist.jp
License: MIT
Classifier: Programming Language :: Python :: 3.11
Classifier: License :: OSI Approved :: MIT License
Classifier: Operating System :: OS Independent
